{
	"class" : {
		 },
	"instance" : {
		"get experience" : "JanKurs 5/10/2013 23:29:10",
		"get health" : "JanKurs 5/10/2013 23:29:10",
		"get position" : "JanKurs 5/10/2013 23:29:10",
		"increase experience points with:" : "JanKurs 5/10/2013 23:29:10",
		"increase health with twenty percent" : "JanKurs 5/10/2013 23:29:10",
		"initialize" : "JanKurs 5/10/2013 21:30",
		"move ten steps forward" : "JanKurs 5/10/2013 23:29:10",
		"set health:" : "JanKurs 5/10/2013 23:29:10",
		"set the damn health:" : "JanKurs 5/10/2013 23:29:10" } }
